odoo/addons/purchase_reception_status/README.rst
odoo/addons/purchase_reception_status/__init__.py
odoo/addons/purchase_reception_status/__manifest__.py
odoo/addons/purchase_reception_status/i18n/es.po
odoo/addons/purchase_reception_status/i18n/fr.po
odoo/addons/purchase_reception_status/i18n/it.po
odoo/addons/purchase_reception_status/i18n/ja.po
odoo/addons/purchase_reception_status/i18n/pt.po
odoo/addons/purchase_reception_status/i18n/purchase_reception_status.pot
odoo/addons/purchase_reception_status/models/__init__.py
odoo/addons/purchase_reception_status/models/purchase_order.py
odoo/addons/purchase_reception_status/readme/CONTRIBUTORS.md
odoo/addons/purchase_reception_status/readme/DESCRIPTION.md
odoo/addons/purchase_reception_status/readme/USAGE.md
odoo/addons/purchase_reception_status/static/description/icon.png
odoo/addons/purchase_reception_status/static/description/index.html
odoo/addons/purchase_reception_status/tests/__init__.py
odoo/addons/purchase_reception_status/tests/test_purchase_reception_status.py
odoo/addons/purchase_reception_status/views/purchase_order.xml
odoo_addon_purchase_reception_status-18.0.1.0.0.4.dist-info/METADATA
odoo_addon_purchase_reception_status-18.0.1.0.0.4.dist-info/WHEEL
odoo_addon_purchase_reception_status-18.0.1.0.0.4.dist-info/top_level.txt
odoo_addon_purchase_reception_status-18.0.1.0.0.4.dist-info/RECORD
